{
	"storyName": "The Hooligans",
	"hideFreeplay": false,
	"weekBackground": "susstage",
	"weekBefore": "monstersweek",
	"freeplayColor": [
		146,
		113,
		253
	],
	"startUnlocked": true,
	"weekCharacters": [
		"",
		"bf",
		"gf"
	],
	"songs": [
		[
			"Rainbow Trololo",
			"eduard",
			[
				191,
				147,
				84
			]
		],
		[
			"Yoinky Sploinky",
			"trollmogus",
			[
				255,
				40,
				40
			]
		],
		[
			"Reminisce",
			"pibbyt",
			[
				207,
				157,
				104
			]
		],
	],
	"hideStoryMode": true,
	"weekName": "hooligansweek"
}
